{
  "sling:resourceType": "wcm/dialogs/dialog",
  "tabs": {
    "sling:resourceType": "wcm/dialogs/components/tabs",
    "generalTab": {
      "sling:resourceType": "wcm/dialogs/components/tab",
      "label": "General",
      "fieldName": {
        "sling:resourceType": "wcm/dialogs/components/include",
        "path": "/apps/typerefinery/components/forms/form/common/fieldName"
      },
      "fieldValue": {
        "sling:resourceType": "wcm/dialogs/components/include",
        "path": "/apps/typerefinery/components/forms/form/common/fieldValue"
      }
    },
    "validationTab": {
      "sling:resourceType": "wcm/dialogs/components/include",
      "path": "/apps/typerefinery/components/dialog/tabs/validation"
    },
    "gridTab": {
      "sling:resourceType": "wcm/dialogs/components/include",
      "path": "/apps/typerefinery/components/dialog/tabs/grid"
    },
    "styleTab": {
      "sling:resourceType": "wcm/dialogs/components/include",
      "path": "/apps/typerefinery/components/dialog/tabs/style"
    },
    "ariaTab": {
      "sling:resourceType": "wcm/dialogs/components/include",
      "path": "/apps/typerefinery/components/dialog/tabs/aria"
    }
  }
}
