{
  "sling:resourceType": "wcm/dialogs/dialog",
  "tabs": {
    "sling:resourceType": "wcm/dialogs/components/tabs",
    "generalTab": {
      "sling:resourceType": "wcm/dialogs/components/tab",
      "label": "General",
      "fieldLabel": {
        "sling:resourceType": "wcm/dialogs/components/textfield",
        "name": "label",
        "label": "Label"
      },
      "fieldName": {
        "sling:resourceType": "wcm/dialogs/components/textfield",
        "name": "name",
        "label": "Name"
      },
      "fieldClass": {
        "sling:resourceType": "wcm/dialogs/components/select",
        "name": "fieldClass",
        "label": "Style",
        "primary": {
          "sling:resourceType": "wcm/dialogs/components/select/selectitem",
          "label": "Primary Button",
          "value": "",
          "selected": true
        },
        "success": {
          "sling:resourceType": "wcm/dialogs/components/select/selectitem",
          "label": "Success Button",
          "value": "p-button-success"
        },
        "warning": {
          "sling:resourceType": "wcm/dialogs/components/select/selectitem",
          "label": "Warning Button",
          "value": "p-button-warning"
        },
        "danger": {
          "sling:resourceType": "wcm/dialogs/components/select/selectitem",
          "label": "Danger Button",
          "value": "p-button-danger"
        },
        "round": {
          "sling:resourceType": "wcm/dialogs/components/select/selectitem",
          "label": "Round Button",
          "value": "p-button-rounded"
        },
        "outlineButton": {
          "sling:resourceType": "wcm/dialogs/components/select/selectitem",
          "label": "Outlined Button",
          "value": "p-button-outlined"
        }

      },
      "fieldValue": {
        "sling:resourceType": "wcm/dialogs/components/textfield",
        "name": "value",
        "label": "Value"
      },
      "buttonSize": {
        "sling:resourceType": "wcm/dialogs/components/select",
        "name": "buttonSize",
        "label": "Size",
        "small": {
          "sling:resourceType": "wcm/dialogs/components/select/selectitem",
          "label": "Small",
          "value": "p-button-sm"
        },
        "normal": {
          "sling:resourceType": "wcm/dialogs/components/select/selectitem",
          "label": "Normal",
          "value": "",
          "selected": true
        },
        "large": {
          "sling:resourceType": "wcm/dialogs/components/select/selectitem",
          "label": "Large",
          "value": "p-button-lg"
        }
      }
    },
    "buttonType": {
      "sling:resourceType": "wcm/dialogs/components/tab",
      "label": "Button Type",
      "cssClasses": {
        "sling:resourceType": "wcm/dialogs/components/select",
        "name": "button",
        "submitButton": {
          "sling:resourceType": "wcm/dialogs/components/select",
          "label": "Submit",
          "selected": true,
          "value": ""
        },
        "resetButton": {
          "sling:resourceType": "wcm/dialogs/components/select",
          "label": "Reset",
          "value": "p-button-reset"
        },
        "normalButton": {
          "sling:resourceType": "wcm/dialogs/components/select",
          "label": "Button",
          "value": "p-button-normalbutton"
        }
      }
    }
  }
}
